COPYING
MANIFEST.in
README.rst
setup.py
BaculaFS.egg-info/PKG-INFO
BaculaFS.egg-info/SOURCES.txt
BaculaFS.egg-info/dependency_links.txt
BaculaFS.egg-info/entry_points.txt
BaculaFS.egg-info/not-zip-safe
BaculaFS.egg-info/requires.txt
BaculaFS.egg-info/top_level.txt
baculafs/Base64.py
baculafs/Catalog.py
baculafs/Database.py
baculafs/FileSystem.py
baculafs/LogFile.py
baculafs/SQL.py
baculafs/__init__.py
baculafs/baculafs
baculafs/junk.py