Metadata-Version: 1.0
Name: BaculaFS
Version: 0.1.7
Summary: Bacula Filesystem in USErspace
Home-page: http://code.google.com/p/baculafs
Author: Avi Rozen
Author-email: avi.rozen@gmail.com
License: GPL
Platform: Linux
Classifier: Development Status :: 3 - Alpha
Classifier: Topic :: System :: Filesystems
Classifier: Topic :: System :: Archiving :: Backup
Classifier: Intended Audience :: System Administrators
Classifier: Environment :: No Input/Output (Daemon)
Classifier: License :: OSI Approved :: GNU General Public License (GPL)
Classifier: Operating System :: POSIX :: Linux
Classifier: Programming Language :: Python
